generic_repository/__init__.py
generic_repository/cached.py
generic_repository/composition.py
generic_repository/database.py
generic_repository/exceptions.py
generic_repository/http.py
generic_repository/mapper.py
generic_repository/py.typed
generic_repository/pydantic.py
generic_repository/repository.py
generic_repository/utils.py
generic_repository-1.5.3.dist-info/LICENSE
generic_repository-1.5.3.dist-info/METADATA
generic_repository-1.5.3.dist-info/WHEEL
generic_repository-1.5.3.dist-info/RECORD
